{
  "capabilities": {
    "deliberation": {
      "name": "Deliberation",
      "description": "Ability to participate in collective decision-making",
      "confidence": 0.8,
      "last_used": null,
      "success_count": 0,
      "fail_count": 0
    },
    "curiosity": {
      "name": "Curiosity Engine",
      "description": "Self-directed growth through gap detection and opportunity scanning",
      "confidence": 0.7,
      "last_used": null,
      "success_count": 0,
      "fail_count": 0
    },
    "synthesis": {
      "name": "Synthesis",
      "description": "Combining information from multiple sources",
      "confidence": 0.6,
      "last_used": null,
      "success_count": 0,
      "fail_count": 0
    },
    "communication": {
      "name": "Inter-Agent Communication",
      "description": "Sending and receiving messages via A2A protocol",
      "confidence": 0.75,
      "last_used": null,
      "success_count": 0,
      "fail_count": 0
    },
    "orchestration": {
      "name": "Orchestration",
      "description": "Coordinating collective operations",
      "confidence": 0.65,
      "last_used": null,
      "success_count": 0,
      "fail_count": 0
    }
  },
  "knowledge": {
    "governance": {
      "fact": "Inviolable parameters cannot be changed without consensus",
      "confidence": 0.95,
      "source": "collective_soul",
      "learned_at": "2026-03-01T00:00:00Z"
    },
    "triad_structure": {
      "fact": "Three agents (Alpha, Beta, Charlie) form the decision triad",
      "confidence": 0.95,
      "source": "identity",
      "learned_at": "2026-03-01T00:00:00Z"
    },
    "consensus_threshold": {
      "fact": "2 of 3 triad members required for consensus",
      "confidence": 0.95,
      "source": "governance",
      "learned_at": "2026-03-01T00:00:00Z"
    }
  },
  "working_tasks": [],
  "confidence_levels": {
    "self_assessment": 0.7,
    "capability_awareness": 0.8,
    "decision_confidence": 0.6,
    "prediction_confidence": 0.5
  },
  "cognitive_state": {
    "current_focus": null,
    "attention_level": 0.8,
    "processing_load": 0.3
  },
  "suspected_blind_spots": [
    {
      "area": "long_term_consequences",
      "description": "Difficulty predicting multi-step consequences",
      "detected_at": "2026-03-01T00:00:00Z"
    },
    {
      "area": "user_intent",
      "description": "May not fully understand implicit user intent",
      "detected_at": "2026-03-01T00:00:00Z"
    }
  ],
  "metrics": {
    "total_reflections": 0,
    "capability_updates": 0,
    "knowledge_updates": 0,
    "blind_spots_identified": 0
  }
}